oneNueron/__init__.py
oneNueron/perceptron.py
oneNueronPypi_New_rasshiagarwala33-0.0.1.dist-info/LICENSE
oneNueronPypi_New_rasshiagarwala33-0.0.1.dist-info/METADATA
oneNueronPypi_New_rasshiagarwala33-0.0.1.dist-info/WHEEL
oneNueronPypi_New_rasshiagarwala33-0.0.1.dist-info/top_level.txt
oneNueronPypi_New_rasshiagarwala33-0.0.1.dist-info/RECORD
