Metadata-Version: 2.1
Name: oneNueronPypi-New-rasshiagarwala33
Version: 0.0.1
Summary: It's an implementation of perceptron
Home-page: https://github.com/pypa/rasshiagarwala33/oneNueronPypi_New
Author: rasshiagarwala33
Author-email: agarwalrashi54321@gmail.com
License: UNKNOWN
Project-URL: Bug Tracker, https://github.com/rasshiagarwala33/oneNueronPypi_New/issues
Platform: UNKNOWN
Classifier: Programming Language :: Python :: 3
Classifier: License :: OSI Approved :: MIT License
Classifier: Operating System :: OS Independent
Requires-Python: >=3.7
License-File: LICENSE
Requires-Dist: numpy
Requires-Dist: tqdm
Requires-Dist: pandas
Requires-Dist: joblib
